<?xml version="1.0" encoding="iso-8859-1"?>
<!-- MP-TV-Series translation file -->
<!-- Nederlands -->
<!-- Last Updated: 1st Dec 2009 -->
<!-- Note: English is the fallback for any strings not found in other languages -->
<strings>
  <string Field="Series" Original="Series">Serie</string>
  <string Field="Series_Plural" Original="Series (Plr)">Series</string>
  <!-- plural -->
  <string Field="Season" Original="Season">Seizoen</string>
  <string Field="Seasons" Original="Seasons">Seizoenen</string>
  <string Field="Episode" Original="Episode">Aflevering</string>
  <string Field="Episodes" Original="Episodes">Afleveringen</string>
  <string Field="Toggle_watched_flag" Original="Toggle watched flag">Bekeken Aan/Uit</string>
  <string Field="Retrieve_Subtitle" Original="Retrieve Subtitle">Ondertiteling Ophalen</string>
  <string Field="Load_via_Torrent" Original="Load via Torrent">Via Torrent Laden</string>
  <string Field="Mark_all_as_watched" Original="Mark all as watched">Markeer alles als bekeken</string>
  <string Field="Mark_all_as_unwatched" Original="Mark all as unwatched">Markeer alles als onbekeken</string>
  <string Field="Hide" Original="Hide">Verberg</string>
  <string Field="Delete" Original="Delete">Verwijder</string>
  <string Field="Remove_series_from_Favourites" Original="Remove series from Favourites">Verwijder uit Favorieten</string>
  <string Field="Add_series_to_Favourites" Original="Add series to Favourites">Voeg toe aan Favorieten</string>
  <string Field="Force_Local_Scan" Original="Force Local Scan ">Forceer lokale scan</string>
  <string Field="Force_Online_Refresh" Original="Force Online Refresh ">Forceer online vernieuwen</string>
  <string Field="In_Progress_with_Barracks" Original="(In Progress)">(Bezig)</string>
  <string Field="Only_show_episodes_with_a_local_file" Original="Only show episodes with a local file">Toon enkel lokale afleveringen</string>
  <string Field="Hide_summary_on_unwatched" Original="Hide the episode's summary on unwatched episodes">Verberg de omschrijving bij niet bekeken afleveringen</string>
  <string Field="on" Original="on">aan</string>
  <string Field="off" Original="off">uit</string>
  <string Field="Play_Random_Episode" Original="Play Random Episode">Speel Willekeurige Aflevering</string>
  <string Field="Play_Random_First_Unwatched_Episode" Original="Play Random First Unwatched Episode">Speel Willekeurige Onbekeken Aflevering</string>
  <string Field="Delete_that_series" Original="Delete that series?">Deze serie verwijderen?</string>
  <string Field="Delete_that_season" Original="Delete that season?">Dit seizoen verwijderen?</string>
  <string Field="Delete_that_episode" Original="Delete that episode?">Deze aflevering verwijderen?</string>
  <string Field="Confirm" Original="Confirm">Bevestig</string>
  <string Field="Completed" Original="Completed">Voltooid</string>
  <string Field="No_subtitles_found" Original="No subtitles found">Geen ondertiteling gevonden</string>
  <string Field="skip_Never_ask_again" Original="Skip / Never ask again">Overslaan / Nooit meer vragen</string>
  <string Field="no_results_found" Original="No results found!">Geen resultaten gevonden!</string>
  <string Field="_Hidden_to_prevent_spoilers_" Original=" * Hidden to prevent spoilers *"> * Verborgen omwille van Spoilers *</string>
  <string Field="Yes" Original="Yes">Ja</string>
  <string Field="No" Original="No">Nee</string>
  <string Field="Error" Original="#Error">#Fout</string>
  <string Field="No_items" Original="No items!">Geen items!</string>
  <string Field="Unknown" Original="Unknown">Onbekend</string>
  <string Field="wrongSkin" Original="Wrong Skin file">Foutief Skin bestand</string>
  <string Field="special" Original="Special">Extra</string>
  <string Field="specials" Original="Specials">Extra's</string>
  <string Field="delPhyiscalWarning" Original="You are about to permanently delete {0} physical file(s).\nWould you like to proceed?">"U staat op het punt om permanent {0} bestand(en) te verwijderen.\nWilt u doorgaan?"</string>
  <string Field="Force_Online_Match" Original="Force Online Match">Forceer Online Overeenkomst</string>
  <string Field="Load_via_NewsLeecher" Original="Load via NewsLeecher">Laad via NewsLeecher</string>
  <string Field="Download" Original="Download">Download</string>
  <string Field="Actions" Original="Actions">Acties</string>
  <string Field="Options" Original="Options">Opties</string>
  <string Field="Genres" Original="Genres">Genres</string>
  <string Field="All" Original="All">Allemaal</string>
  <string Field="Latest" Original="Latest">Laatste</string>
  <string Field="Channels" Original="Channels">Kanalen</string>
  <string Field="Unwatched" Original="Unwatched">Onbekeken</string>
  <string Field="Favourites" Original="Favourites">Favorieten</string>
  <string Field="updateMI" Original="Update Mediainfo of local file">Media Info Bijwerken</string>
  <string Field="RateSeries" Original="Rate this Series">Waardeer deze serie</string>
  <string Field="RateEpisode" Original="Rate this Episode">Waardeer deze aflevering</string>
  <string Field="ResetRating" Original="Reset Rating">Waardering Herstellen</string>
  <string Field="AskToRate" Original="Ask me to rate unrated episodes">Vraag me om ongewaardeerde afleveringen te waarderen</string>
  <string Field="DontAskToRate" Original="Don't ask me to rate again">Vraag me niet opnieuw om te waarderen</string>
  <string Field="RatingStar" Original="Star">Ster</string>
  <string Field="RatingStars" Original="Stars">Sterren</string>
  <string Field="ChangeView" Original="Change View">Wijzig Weergave</string>
  <string Field="ChangeViewFast" Original="Immediatly Change Views">Onmiddelijk Weergaves Wijzigen</string>
  <string Field="FanArt" Original="Fanart">Fanart</string>
  <string Field="FanListAll" Original="List all Fanart for this Series">Toon alle Fanart voor deze serie</string>
  <string Field="FanArtGetAndUse" Original="Download Fanart and Use">Download en Gebruik Fanart</string>
  <string Field="FanArtGet" Original="Download Fanart">Download Fanart</string>
  <string Field="FanArtUse" Original="Set Fanart as Default">Fanart als Standaard instellen</string>
  <string Field="FanArtDelete" Original="Delete Fanart">Verwijder Fanart</string>
  <string Field="FanDownloadingStatus" Original="Downloading {0} Fanart...">Downloaden van {0} Fanart...</string>
  <string Field="FanArtLocal" Original="Local">Lokaal</string>
  <string Field="FanArtOnline" Original="Remote">Op afstand</string>
  <string Field="FanArtOnlineLoading" Original="Loading {0} of {1} Fanart...">Bezig met laden {0} van {1} Fanart...</string>
  <string Field="FanArtRandom" Original="Display random Fanart">Toon willekeurige Fanart</string>
  <string Field="FanArtNoneFound" Original="No Fanart could be found">Geen Fanart kon worden gevonden</string>
  <string Field="CFS_Choose_Item" Original="Choose item">Kies item</string>
  <string Field="CFS_Select_Matching_Item" Original="Select matching item:">Selecteer passend item:</string>
  <string Field="CFS_Search_Again" Original="Search again">Opnieuw zoeken</string>
  <string Field="CFS_Select_Matching_Subitle_File" Original="Select Matching Subtitle File">Selecteer Passend Ondertitelings Bestand</string>
  <string Field="CFS_Subtitle_Episode" Original="Choose item">Aflevering:</string>
  <string Field="CFS_Matching_Subtitles" Original="Matching Subtitles">Passende Ondertitelingen</string>
  <string Field="CFS_Choose_Correct_Series" Original="Choose Correct Series">Kies Correcte Serie</string>
  <string Field="CFS_Available_Series" Original="Available Series">Beschikbare Series</string>
  <string Field="CFS_Select_Correct_Subtitle_Version" Original="Select desired subtitles version">Selecteer gewenste ondertitelings versie</string>
  <string Field="CFS_Select_Version" Original="Version:">Versie:</string>
  <string Field="CFS_Choose_Correct_Episode" Original="Choose Correct Episode">Kies Correcte Aflevering</string>
  <string Field="CFS_Local_Episode_Index" Original="Local Episiode index:">Lokale Afleveringen index:</string>
  <string Field="CFS_Available_Episode_List" Original="Available Episode list:">Beschikbare Afleveringen lijst:</string>
  <string Field="CFS_Choose_Search_Site" Original="Choose search site:">Kies zoeksite:</string>
  <string Field="CFS_List_Search_Site" Original="List of search sites:">Lijst met zoeksites:</string>
  <string Field="CFS_Found_Torrents" Original="Found torrents:">Gevonden torrents:</string>
  <string Field="CFS_Looking_For" Original="Looking for:">Bezig met zoeken naar:</string>
  <string Field="CFS_Choose_Correct_Season" Original="Choose correct season">Kies correct seizoen</string>
  <string Field="CFS_Local_Season_Index" Original="Local Season index:">Lokale Seizoenen index:</string>
  <string Field="CFS_Available_Seasons" Original="Available Seasons list:">Beschikbare Seizoenen lijst:</string>
  <string Field="CYN_Subtitle_File_Replace" Original="Subtitle File Replace">Ondertitelings bestand vervangen</string>
  <string Field="CYN_Old_Subtitle_Replace" Original="Old subtitle File present: overwrite?">Oud ondertitelings bestand aanwezig: overschrijven?</string>
  <string Field="RecentlyAdded" Original="Recently Added">Recent Toegevoegd</string>
  <string Field="TVDB_ERROR_TITLE" Original="theTVDB Error">theTVDB Fout</string>
  <string Field="TVDB_INFO_TITLE" Original="theTVDB">theTVDB</string>
  <string Field="TVDB_INFO_ACCOUNTID_1" Original="Account Identifier is not set">Account Identificatie is niet ingesteld</string>
  <string Field="TVDB_INFO_ACCOUNTID_2" Original="Enter your online account ID in Configuration">Voer uw online account ID in bij Configuratie</string>
  <string Field="TVDB_ERROR_UNAVAILABLE" Original="TheTVDB.com is currently unavailable, try again later">TheTVDB.com is momenteel niet beschikbaar, probeer later opnieuw</string>
  <string Field="NETWORK_ERROR_UNAVAILABLE" Original="Network connection is unavailable, check connection and try again">Netwerk verbinding is niet beschikbaar, controleer verbinding en probeer opnieuw</string>
  <string Field="ShowSeriesFanart" Original="Show Fanart in Series View">Toon Fanart in Serie Weergave</string>
  <string Field="ChangeLayout" Original="Change Layout">Wijzig Layout</string>
  <string Field="UseOnlineFavourites" Original="Use Online Favourites">Gebruik online favorieten</string>
  <string Field="AddToPlaylist" Original="Add To Playlist">Aan afspeellijst toevoegen</string>
  <string Field="FanartDisableLabel" Original="Disabled">Uitgeschakeld</string>
  <string Field="FanartMenuEnable" Original="Enable Fanart">Fanart inschakelen</string>
  <string Field="FanartMenuDisable" Original="Disable Fanart">Fanart uitschakelen</string>
  <string Field="SortByStrings" Original="SortByStrings">the|a|an</string>
  <!--Additional ones should be added for other languages, dont translate existing ones as they will be used as well-->
  <string Field="LayoutList" Original="List">Lijst</string>
  <string Field="LayoutListBanners" Original="List Banners">Lijst met Banners</string>
  <string Field="LayoutListPosters" Original="List Posters">Lijst met Posters</string>
  <string Field="LayoutWideBanners" Original="Wide Banners">Breede Banners</string>
  <string Field="LayoutFilmstrip" Original="Filmstrip">Filmstrip</string>
  <string Field="LayoutSmallIcons" Original="Small Icons">Kleine Iconen</string>
  <string Field="ButtonAutoPlay" Original="Auto Play">Automatisch Afspelen</string>
  <string Field="ButtonSwitchView" Original="Switch View">Wissel Weergave</string>
  <string Field="ButtonRunImport" Original="Run Import">Start Importeren</string>
  <string Field="ButtonChangeLayout" Original="Change Layout">Wijzig Layout</string>
  <string Field="ButtonOptions" Original="Options">Opties</string>
  <string Field="FanArtFilter" Original="Filter">Filter</string>
  <string Field="FanArtFilterAll" Original="All">Allemaal</string>
  <string Field="ButtonRandomFanart" Original="Random Fanart">Willekeurige Fanart</string>
  <string Field="LabelResolution" Original="Resolution:">Resolutie:</string>
  <string Field="LabelChosen" Original="Chosen:">Gekozen:</string>
  <string Field="LabelDisabled" Original="Disabled:">Uitgeschakeld:</string>
  <string Field="ResetUserSelections" Original="Reset User Selections">Gebruiker Selecties Herstellen</string>
  <string Field="DeleteFromDisk" Original="Delete from Disk">Verwijder van schijf</string>
  <string Field="DeleteFromDatabase" Original="Delete from Database">Verwijder uit database</string>
  <string Field="DeleteFromFileDatabase" Original="Delete from Disk and Database">Verwijder van schijf en uit database</string>
  <string Field="RateDialogLabel" Original="Select Your Rating for {0}">Selecteer uw waardering voor {0}</string>
  <string Field="Hide_thumbnail_on_unwatched" Original="Hide Spoiler Thumbnails">Verberg Spoiler Miniaturen</string>
  <!-- Rate Descriptions - 5 Stars-->
  <string Field="RateFiveStarOne" Original="Terrible">Slecht</string>
  <string Field="RateFiveStarTwo" Original="">Matig</string>
  <string Field="RateFiveStarThree" Original="">Goed</string>
  <string Field="RateFiveStarFour" Original="">Heel Goed</string>
  <string Field="RateFiveStarFive" Original="">Uitstekend</string>
  <!-- Rate Descriptions - 10 Stars-->
  <string Field="RateTenStarOne" Original="Abysmal">Verschrikkelijk</string>
  <string Field="RateTenStarTwo" Original="Terrible">Heel Slecht</string>
  <string Field="RateTenStarThree" Original="Bad">Slecht</string>
  <string Field="RateTenStarFour" Original="Poor">Ondermaats</string>
  <string Field="RateTenStarFive" Original="Mediocre">Matig</string>
  <string Field="RateTenStarSix" Original="Fair">Bovenmatig</string>
  <string Field="RateTenStarSeven" Original="Good">Goed</string>
  <string Field="RateTenStarEight" Original="Great">Heel Goed</string>
  <string Field="RateTenStarNine" Original="Superb">Geweldig</string>
  <string Field="RateTenStarTen" Original="Perfect">Uitstekend</string>
  <string Field="ContentRating" Original="Content Rating">Inhoud Waardering</string>
  <string Field="ViewTags" Original="View Tags">Weergave Tags</string>
  <string Field="AddViewTag" Original="Add Series to View Tag">Voeg Serie toe aan Weergave</string>
  <string Field="RemoveViewTag" Original="Remove Series from View Tag">Verwijder Serie uit Weergave</string>
  <string Field="NewViewTag" Original="New Tag">Nieuwe Weergave</string>
  <string Field="CycleSeriesBanner" Original="Cycle Series Banner">Roteer Serie Banner</string>
  <string Field="CycleSeasonBanner" Original="Cycle Season Poster">Roteer Seizoen Poster</string>
  <string Field="CycleSeriesPoster" Original="Cycle Series Poster">Roteer Serie Poster</string>
  <string Field="FanartRandomInterval" Original="Fanart Timer Interval">Fanart Timer Interval</string>
  <string Field="FanartIntervalFiveSeconds" Original="5 Seconds">5 Seconden</string>
  <string Field="FanartIntervalTenSeconds" Original="10 Seconds">10 Seconden</string>
  <string Field="FanartIntervalFifteenSeconds" Original="15 Seconds">15 Seconden</string>
  <string Field="FanartIntervalThirtySeconds" Original="30 Seconds">30 Seconden</string>
  <string Field="FanartIntervalFortyFiveSeconds" Original="45 Seconds">45 Seconden</string>
  <string Field="FanartIntervalSixtySeconds" Original="60 Seconds">60 Seconden</string>
  <string Field="NoPlaylistsFound" Original="No Playlists found in:">Geen afspeellijst gevonden in:</string>
  <string Field="PinCode" Original="Pin Code">PIN Code</string>
  <string Field="PinCodeIncorrectLine1" Original="The entered pin code is incorrect">De ingevoerde PIN code is niet correct</string>
  <string Field="PinCodeIncorrectLine2" Original="Press OK to try again">Druk op OK om opnieuw te proberen</string>
  <string Field="ParentalControlLocked" Original="Lock Views">Vergrendel Weergaves</string>
  <string Field="ViewIsLocked" Original="View Locked">Bekijk Vergrendelde</string>
  <string Field="PinCodeDlgLabel1" Original="The view {0} is locked">De weergave "{0}" is vergrendeld</string>
  <string Field="PinCodeDlgLabel2" Original="Enter in 4 Digit Pin Code to proceed:">Voer 4 cijferige PIN code in om verder te gaan:</string>
  <string Field="PinCodeMessageIncorrect" Original="Pin Incorrect">PIN Foutief</string>
  <string Field="Continuing" Original="Continuing Series">Lopende Series</string>
  <string Field="Ended" Original="Ended Series">Afgelopen Series</string>
  <string Field="HighDefinition" Original="High Definition">Hoge Definitie</string>
  <string Field="StandardDefinition" Original="Standard Defintion">Standaard Definitie</string>
  <string Field="Top10Online" Original="Top 10 (Online)">Top 10 (Online)</string>
  <string Field="Top10User" Original="Top 10 (User)">Top 10 (Gebruiker)</string>
  <string Field="Top25Online" Original="Top 25 (Online)">Top 25 (Online)</string>
  <string Field="Top25User" Original="Top 25 (User)">Top 25(Gebruiker)</string>
  <string Field="Subtitles" Original="Subtitles">Ondertitels</string>
  <string Field="MultiAudio" Original="Multiple Audio Tracks">Meerdere Audio Sporen</string>
  <string Field="OnlineFavourites" Original="Online Favourites">Online Favorieten</string>
  <string Field="Actors" Original="Actors">Acteurs</string>
  <string Field="RemovableMedia" Original="Removable Media">Verwijderbare Media</string>
  <string Field="LocalMedia" Original="Local Media">Lokale Media</string>
  <string Field="AdultSeries" Original="Adult Series">Volwassen Series</string>
  <string Field="KidsSeries" Original="Kids Series">Kinder Series</string>
  <string Field="ClearFanartCache" Original="Clear Fanart Cache">Ledig Fanart Cache</string>
</strings>